{"version":1,"sessions":{"adf652bc-ea8d-4167-a949-9517ebdf114c":{"updatedAt":1783453982282,"files":{"C:\\Users\\Ahmed\\Documents\\ESATprep\\src\\components\\ui\\Origin.jsx":{"editCount":1,"findings":[]},"C:\\Users\\Ahmed\\Documents\\ESATprep\\src\\pages\\QuestionBank.jsx":{"editCount":3,"findings":[]},"C:\\Users\\Ahmed\\Documents\\ESATprep\\src\\main.jsx":{"editCount":2,"findings":[]},"C:\\Users\\Ahmed\\Documents\\ESATprep\\src\\index.css":{"editCount":0,"findings":["overused-font:99:plus jakarta sans"]}}},"a0651a2d-ad46-4fdc-b811-3512ad64a17e":{"updatedAt":1783370179731,"files":{"C:\\Users\\Ahmed\\Documents\\ESATprep\\src\\lib\\supabase.js":{"editCount":1,"findings":[]},"C:\\Users\\Ahmed\\Documents\\ESATprep\\src\\lib\\cloudSync.js":{"editCount":1,"findings":[]},"C:\\Users\\Ahmed\\Documents\\ESATprep\\src\\lib\\session.js":{"editCount":1,"findings":[]},"C:\\Users\\Ahmed\\Documents\\ESATprep\\src\\components\\auth\\AuthGate.jsx":{"editCount":1,"findings":[]},"C:\\Users\\Ahmed\\Documents\\ESATprep\\src\\pages\\SignIn.jsx":{"editCount":1,"findings":[]},"C:\\Users\\Ahmed\\Documents\\ESATprep\\src\\pages\\Admin.jsx":{"editCount":5,"findings":[]}}},"6a9cea7e-f933-4879-896c-d4b2c42f320a":{"updatedAt":1783368321395,"files":{"C:\\Users\\Ahmed\\Documents\\ESATprep\\src\\data\\notes_content.js":{"editCount":1,"findings":[]},"C:\\Users\\Ahmed\\Documents\\ESATprep\\src\\pages\\Notes.jsx":{"editCount":1,"findings":[]},"C:\\Users\\Ahmed\\Documents\\ESATprep\\src\\pages\\QuestionBank.jsx":{"editCount":4,"findings":[]},"C:\\Users\\Ahmed\\Documents\\ESATprep\\src\\App.jsx":{"editCount":3,"findings":[]},"C:\\Users\\Ahmed\\Documents\\ESATprep\\src\\index.css":{"editCount":0,"findings":["overused-font:99:plus jakarta sans"]},"C:\\Users\\Ahmed\\Documents\\ESATprep\\src\\lib\\utils.js":{"editCount":1,"findings":[]},"C:\\Users\\Ahmed\\Documents\\ESATprep\\src\\components\\ui\\Modal.jsx":{"editCount":1,"findings":[]},"C:\\Users\\Ahmed\\Documents\\ESATprep\\src\\components\\ui\\Button.jsx":{"editCount":1,"findings":[]},"C:\\Users\\Ahmed\\Documents\\ESATprep\\src\\components\\tracker\\HabitDay.jsx":{"editCount":1,"findings":[]},"C:\\Users\\Ahmed\\Documents\\ESATprep\\src\\components\\tracker\\CalendarGrid.jsx":{"editCount":1,"findings":[]},"C:\\Users\\Ahmed\\Documents\\ESATprep\\src\\pages\\HabitTracker.jsx":{"editCount":1,"findings":[]},"C:\\Users\\Ahmed\\Documents\\ESATprep\\src\\lib\\achievements.js":{"editCount":1,"findings":[]},"C:\\Users\\Ahmed\\Documents\\ESATprep\\src\\pages\\Insights.jsx":{"editCount":3,"findings":[]},"C:\\Users\\Ahmed\\Documents\\ESATprep\\src\\lib\\aiContext.js":{"editCount":1,"findings":[]},"C:\\Users\\Ahmed\\Documents\\ESATprep\\src\\pages\\MockHistory.jsx":{"editCount":4,"findings":[]}}},"84110e68-dc39-4b95-93dd-d0f31a38919b":{"updatedAt":1783141410123,"files":{"C:\\Users\\Ahmed\\Documents\\ESATprep\\src\\lib\\studentModel.js":{"editCount":1,"findings":[]}}},"9eee3c27-fcbb-4a39-8197-4e086bfb7440":{"updatedAt":1783140611383,"files":{"C:\\Users\\Ahmed\\Documents\\ESATprep\\src\\lib\\studentModel.js":{"editCount":3,"findings":[]},"C:\\Users\\Ahmed\\Documents\\ESATprep\\src\\lib\\studentModel.test.js":{"editCount":2,"findings":[]},"C:\\Users\\Ahmed\\Documents\\ESATprep\\src\\pages\\Dashboard.jsx":{"editCount":11,"findings":[]},"C:\\Users\\Ahmed\\Documents\\ESATprep\\src\\components\\ui\\ThreeState.jsx":{"editCount":1,"findings":[]},"C:\\Users\\Ahmed\\Documents\\ESATprep\\src\\pages\\Insights.jsx":{"editCount":3,"findings":[]},"C:\\Users\\Ahmed\\Documents\\ESATprep\\src\\App.jsx":{"editCount":3,"findings":[]},"C:\\Users\\Ahmed\\Documents\\ESATprep\\src\\index.css":{"editCount":0,"findings":["overused-font:99:plus jakarta sans"]}}},"a1eed69f-ed3f-418d-a9a7-c246b2b17d32":{"updatedAt":1783071621920,"files":{"C:\\Users\\Ahmed\\Documents\\ESATprep\\src\\lib\\mockScore.js":{"editCount":1,"findings":[]},"C:\\Users\\Ahmed\\Documents\\ESATprep\\src\\components\\ui\\Diagram.jsx":{"editCount":2,"findings":[]},"C:\\Users\\Ahmed\\Documents\\ESATprep\\src\\pages\\QuestionBank.jsx":{"editCount":4,"findings":[]},"C:\\Users\\Ahmed\\Documents\\ESATprep\\src\\pages\\MockExam.jsx":{"editCount":8,"findings":[]},"C:\\Users\\Ahmed\\Documents\\ESATprep\\src\\pages\\MockHistory.jsx":{"editCount":1,"findings":[]},"C:\\Users\\Ahmed\\Documents\\ESATprep\\src\\App.jsx":{"editCount":3,"findings":[]},"C:\\Users\\Ahmed\\Documents\\ESATprep\\src\\index.css":{"editCount":0,"findings":["overused-font:99:plus jakarta sans"]},"C:\\Users\\Ahmed\\Documents\\ESATprep\\src\\lib\\diagrams.js":{"editCount":1,"findings":[]}}},"2f3b865b-d0c4-4028-a66c-72cb1c48efa4":{"updatedAt":1783070414778,"files":{"C:\\Users\\Ahmed\\Documents\\ESATprep\\src\\lib\\errorTags.js":{"editCount":1,"findings":[]},"C:\\Users\\Ahmed\\Documents\\ESATprep\\src\\lib\\reviewQueue.js":{"editCount":1,"findings":[]},"C:\\Users\\Ahmed\\Documents\\ESATprep\\src\\lib\\insights.js":{"editCount":1,"findings":[]},"C:\\Users\\Ahmed\\Documents\\ESATprep\\src\\pages\\QuestionBank.jsx":{"editCount":6,"findings":[]},"C:\\Users\\Ahmed\\Documents\\ESATprep\\src\\pages\\Insights.jsx":{"editCount":1,"findings":[]},"C:\\Users\\Ahmed\\Documents\\ESATprep\\src\\App.jsx":{"editCount":3,"findings":[]},"C:\\Users\\Ahmed\\Documents\\ESATprep\\src\\index.css":{"editCount":0,"findings":["overused-font:99:plus jakarta sans"]},"C:\\Users\\Ahmed\\Documents\\ESATprep\\vite.config.js":{"editCount":1,"findings":[]},"C:\\Users\\Ahmed\\Documents\\ESATprep\\src\\lib\\reviewQueue.test.js":{"editCount":3,"findings":[]},"C:\\Users\\Ahmed\\Documents\\ESATprep\\src\\lib\\insights.test.js":{"editCount":1,"findings":[]}}},"c7fa8d51-6919-423f-82e5-d8bac109bb91":{"updatedAt":1783069522772,"files":{"C:\\Users\\Ahmed\\Documents\\ESATprep\\src\\hooks\\useLocalStorage.js":{"editCount":1,"findings":[]},"C:\\Users\\Ahmed\\Documents\\ESATprep\\src\\lib\\eventLog.js":{"editCount":1,"findings":[]},"C:\\Users\\Ahmed\\Documents\\ESATprep\\src\\lib\\moduleMap.js":{"editCount":1,"findings":[]},"C:\\Users\\Ahmed\\Documents\\ESATprep\\src\\lib\\utils.js":{"editCount":1,"findings":[]},"C:\\Users\\Ahmed\\Documents\\ESATprep\\src\\components\\ui\\Card.jsx":{"editCount":1,"findings":[]},"C:\\Users\\Ahmed\\Documents\\ESATprep\\src\\components\\ui\\TechniqueRenderer.jsx":{"editCount":1,"findings":[]},"C:\\Users\\Ahmed\\Documents\\ESATprep\\src\\pages\\QuestionBank.jsx":{"editCount":2,"findings":[]},"C:\\Users\\Ahmed\\Documents\\ESATprep\\src\\hooks\\useTheme.js":{"editCount":1,"findings":[]},"C:\\Users\\Ahmed\\Documents\\ESATprep\\src\\pages\\History.jsx":{"editCount":1,"findings":[]},"C:\\Users\\Ahmed\\Documents\\ESATprep\\src\\App.jsx":{"editCount":1,"findings":[]},"C:\\Users\\Ahmed\\Documents\\ESATprep\\src\\index.css":{"editCount":0,"findings":["overused-font:99:plus jakarta sans"]}}}}}